rocketformulas/__init__.py
rocketformulas/core.py
rocketformulas-1.0.0.dist-info/licenses/LICENSE
rocketformulas-1.0.0.dist-info/METADATA
rocketformulas-1.0.0.dist-info/WHEEL
rocketformulas-1.0.0.dist-info/top_level.txt
rocketformulas-1.0.0.dist-info/RECORD
