Metadata-Version: 2.4
Name: rocketformulas
Version: 1.0.0
Summary: A Python library providing basic formulas for rocket engine performance and analysis.
Author: Amandeep Singh, Tuiba Ashraf
Author-email: amandeepoct97@gmail.com,tuiba.ashraf107@gmail.com
License: MIT
Classifier: Programming Language :: Python :: 3
Classifier: License :: OSI Approved :: MIT License
Classifier: Operating System :: OS Independent
Classifier: Intended Audience :: Science/Research
Requires-Python: >=3.8
License-File: LICENSE
Requires-Dist: numpy>=1.24.0
Requires-Dist: matplotlib>=3.7.0
Dynamic: author
Dynamic: author-email
Dynamic: classifier
Dynamic: description
Dynamic: description-content-type
Dynamic: license
Dynamic: license-file
Dynamic: requires-dist
Dynamic: requires-python
Dynamic: summary
